aieng_platform_onboard/__init__.py
aieng_platform_onboard/cli.py
aieng_platform_onboard/utils.py
aieng_platform_onboard/admin/__init__.py
aieng_platform_onboard/admin/cli.py
aieng_platform_onboard/admin/delete_participants.py
aieng_platform_onboard/admin/setup_participants.py
aieng_platform_onboard/admin/utils.py
aieng_platform_onboard-0.5.0.dist-info/METADATA
aieng_platform_onboard-0.5.0.dist-info/WHEEL
aieng_platform_onboard-0.5.0.dist-info/entry_points.txt
aieng_platform_onboard-0.5.0.dist-info/licenses/LICENSE.md
aieng_platform_onboard-0.5.0.dist-info/RECORD
