Metadata-Version: 2.4
Name: aieng-platform-onboard
Version: 0.5.0
Summary: CLI tool for onboarding participants to AI Engineering bootcamps
Author-email: Vector AI Engineering <ai_engineering@vectorinstitute.ai>
License-Expression: Apache-2.0
License-File: LICENSE.md
Requires-Python: >=3.12
Requires-Dist: authlib==1.6.6
Requires-Dist: filelock==3.20.3
Requires-Dist: firebase-admin>=6.5.0
Requires-Dist: google-auth>=2.29.0
Requires-Dist: google-cloud-firestore>=2.18.0
Requires-Dist: google-cloud-secret-manager>=2.20.0
Requires-Dist: google-cloud-storage
Requires-Dist: openai>=1.0.0
Requires-Dist: pandas>=2.3.3
Requires-Dist: python-dotenv>=1.0.0
Requires-Dist: requests>=2.31.0
Requires-Dist: rich>=13.0.0
Requires-Dist: urllib3==2.6.3
Requires-Dist: virtualenv==20.36.1
Requires-Dist: weaviate-client>=4.0.0
